[{"name": "BLEU", "score": 4.9, "signature": "nrefs:1|case:mixed|eff:no|tok:13a|smooth:exp|version:2.4.2", "verbose_score": "38.7/9.8/2.8/1.0 (BP = 0.864 ratio = 0.873 hyp_len = 82290 ref_len = 94277)", "nrefs": "1", "case": "mixed", "eff": "no", "tok": "13a", "smooth": "exp", "version": "2.4.2"}, {"name": "chrF2++", "score": 27.5, "signature": "nrefs:1|case:mixed|eff:yes|nc:6|nw:2|space:no|version:2.4.2", "nrefs": "1", "case": "mixed", "eff": "yes", "nc": "6", "nw": "2", "space": "no", "version": "2.4.2"}, {"name": "TER", "score": 91.8, "signature": "nrefs:1|case:lc|tok:tercom|norm:no|punct:yes|asian:no|version:2.4.2", "nrefs": "1", "case": "lc", "tok": "tercom", "norm": "no", "punct": "yes", "asian": "no", "version": "2.4.2"}, {"name": "NIST", "score": 2.83573009047991, "implementation": "nltk.translate.nist_score.corpus_nist", "tok": "nltk.word_tokenize", "tok_preserve_line": "yes", "version": "3.8.1"}, {"name": "METEOR", "score": 0.25066640430807396, "implementation": "evaluate", "version": "0.4.1"}, {"name": "rouge1", "score": 0.3261584191277578, "implementation": "evaluate", "version": "0.4.1", "use_aggregator": "True", "use_stemmer": "True"}, {"name": "rouge2", "score": 0.08493801625226849, "implementation": "evaluate", "version": "0.4.1", "use_aggregator": "True", "use_stemmer": "True"}, {"name": "rougeL", "score": 0.25113640590603653, "implementation": "evaluate", "version": "0.4.1", "use_aggregator": "True", "use_stemmer": "True"}, {"name": "BERTScore", "score": 0.246, "aggregation": "mean", "metric": "F1", "model_type": "microsoft/deberta-xlarge-mnli", "version": "0.3.13", "rescale_with_baseline": true, "truncate above characters": 4000}, {"name": "BLEURT", "score": 0.39591305576413444, "aggregation": "mean", "implementation": "evaluate", "version": "0.4.1"}]