[{"name": "BLEU", "score": 8.4, "signature": "nrefs:1|case:mixed|eff:no|tok:13a|smooth:exp|version:2.4.2", "verbose_score": "46.2/14.7/5.2/2.1 (BP = 0.904 ratio = 0.908 hyp_len = 85602 ref_len = 94277)", "nrefs": "1", "case": "mixed", "eff": "no", "tok": "13a", "smooth": "exp", "version": "2.4.2"}, {"name": "chrF2++", "score": 33.1, "signature": "nrefs:1|case:mixed|eff:yes|nc:6|nw:2|space:no|version:2.4.2", "nrefs": "1", "case": "mixed", "eff": "yes", "nc": "6", "nw": "2", "space": "no", "version": "2.4.2"}, {"name": "TER", "score": 82.5, "signature": "nrefs:1|case:lc|tok:tercom|norm:no|punct:yes|asian:no|version:2.4.2", "nrefs": "1", "case": "lc", "tok": "tercom", "norm": "no", "punct": "yes", "asian": "no", "version": "2.4.2"}, {"name": "NIST", "score": 3.78529248423651, "implementation": "nltk.translate.nist_score.corpus_nist", "tok": "nltk.word_tokenize", "tok_preserve_line": "yes", "version": "3.8.1"}, {"name": "METEOR", "score": 0.30897285038728106, "implementation": "evaluate", "version": "0.4.1"}, {"name": "rouge1", "score": 0.4002007099809004, "implementation": "evaluate", "version": "0.4.1", "use_aggregator": "True", "use_stemmer": "True"}, {"name": "rouge2", "score": 0.13058161883479005, "implementation": "evaluate", "version": "0.4.1", "use_aggregator": "True", "use_stemmer": "True"}, {"name": "rougeL", "score": 0.3223177503288054, "implementation": "evaluate", "version": "0.4.1", "use_aggregator": "True", "use_stemmer": "True"}, {"name": "BLEURT", "score": 0.4511515286658225, "aggregation": "mean", "implementation": "evaluate", "version": "0.4.1"}, {"name": "BERTScore", "score": 0.368, "aggregation": "mean", "metric": "F1", "model_type": "microsoft/deberta-xlarge-mnli", "version": "0.3.13", "rescale_with_baseline": true, "truncate above characters": 4000}]