[{"name": "BLEU", "score": 7.0, "signature": "nrefs:1|case:mixed|eff:no|tok:13a|smooth:exp|version:2.4.2", "verbose_score": "43.3/12.5/4.0/1.5 (BP = 0.931 ratio = 0.934 hyp_len = 88025 ref_len = 94277)", "nrefs": "1", "case": "mixed", "eff": "no", "tok": "13a", "smooth": "exp", "version": "2.4.2"}, {"name": "chrF2++", "score": 32.3, "signature": "nrefs:1|case:mixed|eff:yes|nc:6|nw:2|space:no|version:2.4.2", "nrefs": "1", "case": "mixed", "eff": "yes", "nc": "6", "nw": "2", "space": "no", "version": "2.4.2"}, {"name": "TER", "score": 85.7, "signature": "nrefs:1|case:lc|tok:tercom|norm:no|punct:yes|asian:no|version:2.4.2", "nrefs": "1", "case": "lc", "tok": "tercom", "norm": "no", "punct": "yes", "asian": "no", "version": "2.4.2"}, {"name": "NIST", "score": 3.5279929650917086, "implementation": "nltk.translate.nist_score.corpus_nist", "tok": "nltk.word_tokenize", "tok_preserve_line": "yes", "version": "3.8.1"}, {"name": "METEOR", "score": 0.29124165135154956, "implementation": "evaluate", "version": "0.4.1"}, {"name": "rouge1", "score": 0.37952403245527516, "implementation": "evaluate", "version": "0.4.1", "use_aggregator": "True", "use_stemmer": "True"}, {"name": "rouge2", "score": 0.11232246252887873, "implementation": "evaluate", "version": "0.4.1", "use_aggregator": "True", "use_stemmer": "True"}, {"name": "rougeL", "score": 0.3002372098003506, "implementation": "evaluate", "version": "0.4.1", "use_aggregator": "True", "use_stemmer": "True"}, {"name": "BERTScore", "score": 0.345, "aggregation": "mean", "metric": "F1", "model_type": "microsoft/deberta-xlarge-mnli", "version": "0.3.13", "rescale_with_baseline": true, "truncate above characters": 4000}, {"name": "BLEURT", "score": 0.4468406239933098, "aggregation": "mean", "implementation": "evaluate", "version": "0.4.1"}]